pynumwork.py
pynumwork-0.1.31.dist-info/WHEEL
pynumwork-0.1.31.dist-info/METADATA
pynumwork-0.1.31.dist-info/RECORD
