Metadata-Version: 2.1
Name: pynumwork
Version: 0.1.31
Summary: Dedicated to Ksenia @milkpink_2 :)
Author: spacecultengineer
Author-email: spacecultengineer@gmail.com
Requires-Python: >=3.9,<4.0
Classifier: Programming Language :: Python :: 3
Classifier: Programming Language :: Python :: 3.9
Classifier: Programming Language :: Python :: 3.10
Classifier: Programming Language :: Python :: 3.11
